bf25_pycounts/__init__.py
bf25_pycounts/bf25_pycounts.py
bf25_pycounts/plotting.py
bf25_pycounts-0.3.1.dist-info/LICENSE
bf25_pycounts-0.3.1.dist-info/METADATA
bf25_pycounts-0.3.1.dist-info/WHEEL
bf25_pycounts-0.3.1.dist-info/RECORD
